[
    {
        "name" : "java.lang.Integer",
        "allDeclaredConstructors" : true,
        "allPublicConstructors" : true,
        "allDeclaredMethods" : true,
        "allPublicMethods" : true,
        "allDeclaredFields" : true,
        "allPublicFields" : true
    },
    {
        "name" : "java.lang.Boolean",
        "allDeclaredConstructors" : true,
        "allPublicConstructors" : true,
        "allDeclaredMethods" : true,
        "allPublicMethods" : true,
        "allDeclaredFields" : true,
        "allPublicFields" : true
    },
    {
        "name" : "sun.net.www.protocol.http.HttpURLConnection",
        "allDeclaredConstructors" : true,
        "allPublicConstructors" : true,
        "allDeclaredMethods" : true,
        "allPublicMethods" : true,
        "allDeclaredFields" : true,
        "allPublicFields" : true
    },
    {
        "name" : "java.net.HttpURLConnection",
        "allDeclaredConstructors" : true,
        "allPublicConstructors" : true,
        "allDeclaredMethods" : true,
        "allPublicMethods" : true,
        "allDeclaredFields" : true,
        "allPublicFields" : true
    },
    {
        "name" : "sun.net.www.http.HttpClient",
        "allDeclaredConstructors" : true,
        "allPublicConstructors" : true,
        "allDeclaredMethods" : true,
        "allPublicMethods" : true,
        "allDeclaredFields" : true,
        "allPublicFields" : true
    },{
        "name" : "java.net.SocketCleanable",
        "allDeclaredConstructors" : true,
        "allPublicConstructors" : true,
        "allDeclaredMethods" : true,
        "allPublicMethods" : true,
        "allDeclaredFields" : true,
        "allPublicFields" : true
    },{
        "name" : "java.io.FileCleanable",
        "allDeclaredConstructors" : true,
        "allPublicConstructors" : true,
        "allDeclaredMethods" : true,
        "allPublicMethods" : true,
        "allDeclaredFields" : true,
        "allPublicFields" : true
    },
    {
        "name" : "java.net.Socket",
        "allDeclaredConstructors" : true,
        "allPublicConstructors" : true,
        "allDeclaredMethods" : true,
        "allPublicMethods" : true,
        "allDeclaredFields" : true,
        "allPublicFields" : true
    },
    {
        "name" : "java.io.FileDescriptor",
        "allDeclaredConstructors" : true,
        "allPublicConstructors" : true,
        "allDeclaredMethods" : true,
        "allPublicMethods" : true,
        "allDeclaredFields" : true,
        "allPublicFields" : true
    },
    {
        "name" : "sun.net.NetworkClient",
        "allDeclaredConstructors" : true,
        "allPublicConstructors" : true,
        "allDeclaredMethods" : true,
        "allPublicMethods" : true,
        "allDeclaredFields" : true,
        "allPublicFields" : true
    },{
        "name" : "java.net.PlainSocketImpl",
        "allDeclaredConstructors" : true,
        "allPublicConstructors" : true,
        "allDeclaredMethods" : true,
        "allPublicMethods" : true,
        "allDeclaredFields" : true,
        "allPublicFields" : true
    },{
        "name" : "java.net.AbstractPlainSocketImpl",
        "allDeclaredConstructors" : true,
        "allPublicConstructors" : true,
        "allDeclaredMethods" : true,
        "allPublicMethods" : true,
        "allDeclaredFields" : true,
        "allPublicFields" : true
    },{
        "name" : "java.net.SocketImpl",
        "allDeclaredConstructors" : true,
        "allPublicConstructors" : true,
        "allDeclaredMethods" : true,
        "allPublicMethods" : true,
        "allDeclaredFields" : true,
        "allPublicFields" : true
    },
    {
        "name" : "java.lang.String",
        "allDeclaredConstructors" : true,
        "allPublicConstructors" : true,
        "allDeclaredMethods" : true,
        "allPublicMethods" : true,
        "allDeclaredFields" : true,
        "allPublicFields" : true
    },
    {
        "name" : "java.lang.Void",
        "allDeclaredConstructors" : true,
        "allPublicConstructors" : true,
        "allDeclaredMethods" : true,
        "allPublicMethods" : true,
        "allDeclaredFields" : true,
        "allPublicFields" : true
    }
]